rspmsg
