Metadata-Version: 1.1
Name: rspmsg
Version: 0.6.3
Summary: A python module for rspmsg
Home-page: https://github.com/darkdarkfruit/rspmsg
Author: darkdarkfruit
Author-email: darkdarkfruit@gmail.com
License: MIT
Platform: any
Classifier: Development Status :: 4 - Beta
Classifier: Intended Audience :: Developers
Classifier: License :: OSI Approved :: MIT License
Classifier: Operating System :: OS Independent
Classifier: Programming Language :: Python
Classifier: Topic :: Internet
Classifier: Topic :: Software Development :: Libraries :: Python Modules
